{
	"name": "Zone1",
	"layers": [
		{
			"name": "Layer 0",
			"overriden": 0,
			"subLayers": [],
			"instances": [
				{
					"type": "Sprite",
					"properties": {
						"initially-visible": true,
						"initial-animation": "Animation 1",
						"initial-frame": 0,
						"enable-collisions": true,
						"live-preview": false
					},
					"uid": 63,
					"instanceVariables": {},
					"behaviors": {},
					"world": {
						"x": 963,
						"y": 529,
						"width": 1926.573826169186,
						"height": 1123.8347319320253,
						"originX": 0.5,
						"originY": 0.5,
						"color": [
							1,
							1,
							1,
							1
						],
						"angle": 0,
						"zElevation": 0
					}
				}
			],
			"sid": 602355310319850,
			"effectTypes": [],
			"isInitiallyVisible": true,
			"isInitiallyInteractive": true,
			"color": [
				1,
				1,
				1,
				1
			],
			"backgroundColor": [
				1,
				1,
				1,
				1
			],
			"isTransparent": false,
			"parallaxX": 1,
			"parallaxY": 1,
			"scaleRate": 1,
			"forceOwnTexture": false,
			"renderingMode": "3d",
			"drawOrder": "z-order",
			"useRenderCells": false,
			"blendMode": "normal",
			"zElevation": 0,
			"global": false
		},
		{
			"name": "Levels",
			"overriden": 0,
			"subLayers": [],
			"instances": [
				{
					"type": "Level1",
					"properties": {
						"initially-visible": true,
						"initial-animation": "Default",
						"initial-frame": 0,
						"enable-collisions": true,
						"live-preview": false
					},
					"uid": 0,
					"instanceVariables": {},
					"behaviors": {},
					"world": {
						"x": 1680,
						"y": 225,
						"width": 124.686271667,
						"height": 124.07008264237791,
						"originX": 0.50152,
						"originY": 0.5,
						"color": [
							1,
							1,
							1,
							1
						],
						"angle": 0,
						"zElevation": 0
					}
				},
				{
					"type": "Level2",
					"properties": {
						"initially-visible": true,
						"initial-animation": "Default",
						"initial-frame": 0,
						"enable-collisions": true,
						"live-preview": false
					},
					"uid": 3,
					"instanceVariables": {},
					"behaviors": {},
					"world": {
						"x": 1446,
						"y": 250,
						"width": 124.685997009,
						"height": 124.07048753248255,
						"originX": 0.50152,
						"originY": 0.5,
						"color": [
							1,
							1,
							1,
							1
						],
						"angle": 0,
						"zElevation": 0
					}
				},
				{
					"type": "Level3",
					"properties": {
						"initially-visible": true,
						"initial-animation": "Default",
						"initial-frame": 0,
						"enable-collisions": true,
						"live-preview": false
					},
					"uid": 4,
					"instanceVariables": {},
					"behaviors": {},
					"world": {
						"x": 1355,
						"y": 403,
						"width": 124.685997009,
						"height": 124.07048753248255,
						"originX": 0.50152,
						"originY": 0.5,
						"color": [
							1,
							1,
							1,
							1
						],
						"angle": 0,
						"zElevation": 0
					}
				},
				{
					"type": "Level4",
					"properties": {
						"initially-visible": true,
						"initial-animation": "Default",
						"initial-frame": 0,
						"enable-collisions": true,
						"live-preview": false
					},
					"uid": 5,
					"instanceVariables": {},
					"behaviors": {},
					"world": {
						"x": 1505,
						"y": 598,
						"width": 124.685997009,
						"height": 124.07048753248255,
						"originX": 0.50152,
						"originY": 0.5,
						"color": [
							1,
							1,
							1,
							1
						],
						"angle": 0,
						"zElevation": 0
					}
				},
				{
					"type": "Level10",
					"properties": {
						"initially-visible": true,
						"initial-animation": "Default",
						"initial-frame": 0,
						"enable-collisions": true,
						"live-preview": false
					},
					"uid": 47,
					"instanceVariables": {},
					"behaviors": {},
					"world": {
						"x": 686,
						"y": 218,
						"width": 124.685997,
						"height": 124.070488,
						"originX": 0.50152,
						"originY": 0.5,
						"color": [
							1,
							1,
							1,
							1
						],
						"angle": 0,
						"zElevation": 0
					}
				},
				{
					"type": "Level11",
					"properties": {
						"initially-visible": true,
						"initial-animation": "Default",
						"initial-frame": 0,
						"enable-collisions": true,
						"live-preview": false
					},
					"uid": 48,
					"instanceVariables": {},
					"behaviors": {},
					"world": {
						"x": 899,
						"y": 79,
						"width": 124.685997,
						"height": 124.070488,
						"originX": 0.50152,
						"originY": 0.5,
						"color": [
							1,
							1,
							1,
							1
						],
						"angle": 0,
						"zElevation": 0
					}
				},
				{
					"type": "Level12",
					"properties": {
						"initially-visible": true,
						"initial-animation": "Default",
						"initial-frame": 0,
						"enable-collisions": true,
						"live-preview": false
					},
					"uid": 49,
					"instanceVariables": {},
					"behaviors": {},
					"world": {
						"x": 1097,
						"y": 76,
						"width": 124.685997,
						"height": 124.070488,
						"originX": 0.50152,
						"originY": 0.5,
						"color": [
							1,
							1,
							1,
							1
						],
						"angle": 0,
						"zElevation": 0
					}
				},
				{
					"type": "Level5",
					"properties": {
						"initially-visible": true,
						"initial-animation": "Default",
						"initial-frame": 0,
						"enable-collisions": true,
						"live-preview": false
					},
					"uid": 50,
					"instanceVariables": {},
					"behaviors": {},
					"world": {
						"x": 1310,
						"y": 715,
						"width": 124.685997,
						"height": 124.070488,
						"originX": 0.50152,
						"originY": 0.5,
						"color": [
							1,
							1,
							1,
							1
						],
						"angle": 0,
						"zElevation": 0
					}
				},
				{
					"type": "Level6",
					"properties": {
						"initially-visible": true,
						"initial-animation": "Default",
						"initial-frame": 0,
						"enable-collisions": true,
						"live-preview": false
					},
					"uid": 51,
					"instanceVariables": {},
					"behaviors": {},
					"world": {
						"x": 1104,
						"y": 826,
						"width": 124.685997,
						"height": 124.070488,
						"originX": 0.50152,
						"originY": 0.5,
						"color": [
							1,
							1,
							1,
							1
						],
						"angle": 0,
						"zElevation": 0
					}
				},
				{
					"type": "Level7",
					"properties": {
						"initially-visible": true,
						"initial-animation": "Default",
						"initial-frame": 0,
						"enable-collisions": true,
						"live-preview": false
					},
					"uid": 52,
					"instanceVariables": {},
					"behaviors": {},
					"world": {
						"x": 974,
						"y": 673,
						"width": 124.685997,
						"height": 124.070488,
						"originX": 0.50152,
						"originY": 0.5,
						"color": [
							1,
							1,
							1,
							1
						],
						"angle": 0,
						"zElevation": 0
					}
				},
				{
					"type": "Level8",
					"properties": {
						"initially-visible": true,
						"initial-animation": "Default",
						"initial-frame": 0,
						"enable-collisions": true,
						"live-preview": false
					},
					"uid": 53,
					"instanceVariables": {},
					"behaviors": {},
					"world": {
						"x": 906,
						"y": 480,
						"width": 124.685997,
						"height": 124.070488,
						"originX": 0.50152,
						"originY": 0.5,
						"color": [
							1,
							1,
							1,
							1
						],
						"angle": 0,
						"zElevation": 0
					}
				},
				{
					"type": "Level9",
					"properties": {
						"initially-visible": true,
						"initial-animation": "Default",
						"initial-frame": 0,
						"enable-collisions": true,
						"live-preview": false
					},
					"uid": 54,
					"instanceVariables": {},
					"behaviors": {},
					"world": {
						"x": 629,
						"y": 447,
						"width": 124.685997,
						"height": 124.070488,
						"originX": 0.50152,
						"originY": 0.5,
						"color": [
							1,
							1,
							1,
							1
						],
						"angle": 0,
						"zElevation": 0
					}
				}
			],
			"sid": 813086453773183,
			"effectTypes": [],
			"isInitiallyVisible": true,
			"isInitiallyInteractive": true,
			"color": [
				1,
				1,
				1,
				1
			],
			"backgroundColor": [
				0.3686274509803922,
				0.3686274509803922,
				0.3686274509803922,
				1
			],
			"isTransparent": true,
			"parallaxX": 1,
			"parallaxY": 1,
			"scaleRate": 1,
			"forceOwnTexture": false,
			"renderingMode": "3d",
			"drawOrder": "z-order",
			"useRenderCells": false,
			"blendMode": "normal",
			"zElevation": 0,
			"global": false
		}
	],
	"sid": 469436589525671,
	"nonworld-instances": [],
	"effectTypes": [],
	"width": 1920,
	"height": 1080,
	"unboundedScrolling": false,
	"vpX": 0.5,
	"vpY": 0.5,
	"projection": "perspective",
	"eventSheet": "Zone1 code"
}